hatch_dependency_coversion/__init__.py
hatch_dependency_coversion/_version.py
hatch_dependency_coversion/const.py
hatch_dependency_coversion/hooks.py
hatch_dependency_coversion/metadata_hook.py
hatch_dependency_coversion/py.typed
hatch_dependency_coversion-0.0.1a4.dist-info/METADATA
hatch_dependency_coversion-0.0.1a4.dist-info/WHEEL
hatch_dependency_coversion-0.0.1a4.dist-info/entry_points.txt
hatch_dependency_coversion-0.0.1a4.dist-info/licenses/LICENSE
hatch_dependency_coversion-0.0.1a4.dist-info/RECORD
