Metadata-Version: 2.4
Name: hatch-dependency-coversion
Version: 0.0.1a4
Summary: Require that specific dependencies of your package are exactly coversioned.
Project-URL: Documentation, https://github.com/Opentrons/hatch-plugins/tree/main/hatch-dependency-coversion#readme
Project-URL: Issues, https://github.com/Opentrons/hatch-plugins/issues
Project-URL: Source, https://github.com/Opentrons/hatch-plugins
Project-URL: Changelog, https://github.com/Opentrons/hatch-plugins/tree/main/hatch-dependency-coversion/CHANGES.md
Author-email: Opentrons Engineering <engineering@opentrons.com>
License-Expression: Apache-2.0
License-File: LICENSE
Keywords: coversioning,hatch,monorepo,version
Classifier: Development Status :: 4 - Beta
Classifier: Framework :: Hatch
Classifier: Programming Language :: Python
Classifier: Programming Language :: Python :: 3.8
Classifier: Programming Language :: Python :: 3.9
Classifier: Programming Language :: Python :: 3.10
Classifier: Programming Language :: Python :: 3.11
Classifier: Programming Language :: Python :: 3.12
Classifier: Programming Language :: Python :: Implementation :: CPython
Classifier: Programming Language :: Python :: Implementation :: PyPy
Requires-Python: >=3.8
Requires-Dist: hatchling<2.0.0,>1.0.0
Requires-Dist: packaging>=22.0
